abcmeta/__init__.py
abcmeta-2.2.1.dist-info/LICENSE
abcmeta-2.2.1.dist-info/METADATA
abcmeta-2.2.1.dist-info/WHEEL
abcmeta-2.2.1.dist-info/top_level.txt
abcmeta-2.2.1.dist-info/RECORD
