Metadata-Version: 2.1
Name: abcmeta
Version: 2.2.1
Summary: Python meta class and abstract method library with restrictions.
Home-page: https://github.com/mortymacs/abcmeta
Author: Morteza NourelahiAlamdari
Author-email: m@0t1.me
License: AGPLv3
Project-URL: Bug Tracker, https://github.com/mortymacs/abcmeta/issues
Classifier: Programming Language :: Python :: 3
Classifier: Programming Language :: Python :: 3.13
Classifier: Programming Language :: Python :: 3.12
Classifier: Programming Language :: Python :: 3.11
Classifier: Programming Language :: Python :: 3.10
Classifier: Programming Language :: Python :: 3.9
Classifier: License :: OSI Approved :: GNU Affero General Public License v3 or later (AGPLv3+)
Classifier: Operating System :: OS Independent
Requires-Python: >=3.9
License-File: LICENSE
